{
  "no_penalty": {
    "confusion_matrix": [
      [
        431,
        48,
        137,
        27,
        40,
        46,
        20,
        66,
        150,
        35
      ],
      [
        47,
        348,
        28,
        39,
        41,
        60,
        96,
        41,
        125,
        175
      ],
      [
        208,
        39,
        275,
        49,
        67,
        111,
        68,
        42,
        114,
        27
      ],
      [
        63,
        64,
        94,
        122,
        85,
        214,
        88,
        57,
        132,
        81
      ],
      [
        91,
        45,
        173,
        63,
        123,
        124,
        119,
        98,
        108,
        56
      ],
      [
        61,
        61,
        101,
        102,
        71,
        331,
        49,
        68,
        99,
        57
      ],
      [
        47,
        66,
        59,
        50,
        84,
        102,
        360,
        73,
        47,
        112
      ],
      [
        81,
        55,
        57,
        53,
        106,
        98,
        66,
        302,
        72,
        110
      ],
      [
        149,
        76,
        82,
        41,
        27,
        80,
        25,
        39,
        433,
        48
      ],
      [
        28,
        179,
        16,
        40,
        26,
        55,
        106,
        93,
        61,
        396
      ]
    ],
    "params": {},
    "accuracy": 0.3121,
    "cv_score": 0.3034400298433489
  },
  "l1_lasso": {
    "confusion_matrix": [
      [
        431,
        51,
        135,
        27,
        38,
        47,
        20,
        66,
        151,
        34
      ],
      [
        46,
        346,
        29,
        37,
        41,
        61,
        98,
        40,
        126,
        176
      ],
      [
        206,
        41,
        274,
        47,
        66,
        109,
        68,
        45,
        118,
        26
      ],
      [
        64,
        64,
        95,
        121,
        84,
        215,
        90,
        56,
        130,
        81
      ],
      [
        92,
        45,
        174,
        61,
        121,
        125,
        121,
        97,
        110,
        54
      ],
      [
        61,
        57,
        103,
        101,
        70,
        335,
        49,
        68,
        99,
        57
      ],
      [
        48,
        65,
        59,
        51,
        80,
        102,
        357,
        76,
        48,
        114
      ],
      [
        82,
        55,
        57,
        51,
        103,
        100,
        65,
        302,
        71,
        114
      ],
      [
        146,
        78,
        85,
        41,
        23,
        81,
        26,
        39,
        435,
        46
      ],
      [
        26,
        179,
        16,
        39,
        26,
        55,
        107,
        91,
        62,
        399
      ]
    ],
    "params": {
      "clf__C": 0.1
    },
    "accuracy": 0.3121,
    "cv_score": 0.3042400258439089
  },
  "l2_ridge": {
    "confusion_matrix": [
      [
        431,
        48,
        137,
        27,
        40,
        46,
        20,
        66,
        150,
        35
      ],
      [
        47,
        348,
        28,
        39,
        41,
        60,
        96,
        41,
        125,
        175
      ],
      [
        208,
        39,
        275,
        49,
        67,
        111,
        68,
        42,
        114,
        27
      ],
      [
        63,
        64,
        94,
        122,
        85,
        214,
        88,
        57,
        132,
        81
      ],
      [
        91,
        45,
        173,
        63,
        123,
        124,
        119,
        98,
        108,
        56
      ],
      [
        61,
        61,
        101,
        102,
        71,
        331,
        49,
        68,
        99,
        57
      ],
      [
        47,
        66,
        59,
        50,
        84,
        102,
        360,
        73,
        47,
        112
      ],
      [
        81,
        55,
        57,
        53,
        106,
        98,
        66,
        302,
        72,
        110
      ],
      [
        149,
        76,
        82,
        41,
        27,
        80,
        25,
        39,
        433,
        48
      ],
      [
        28,
        179,
        16,
        40,
        26,
        55,
        106,
        93,
        61,
        396
      ]
    ],
    "params": {
      "clf__C": 10
    },
    "accuracy": 0.3121,
    "cv_score": 0.3034200302433409
  },
  "elasticnet": {
    "confusion_matrix": [
      [
        431,
        50,
        134,
        27,
        39,
        47,
        20,
        66,
        152,
        34
      ],
      [
        47,
        347,
        29,
        37,
        41,
        61,
        96,
        41,
        124,
        177
      ],
      [
        206,
        40,
        274,
        47,
        66,
        111,
        69,
        44,
        116,
        27
      ],
      [
        64,
        63,
        95,
        121,
        85,
        214,
        87,
        57,
        132,
        82
      ],
      [
        91,
        45,
        173,
        63,
        122,
        123,
        120,
        98,
        109,
        56
      ],
      [
        62,
        59,
        104,
        100,
        70,
        333,
        49,
        67,
        99,
        57
      ],
      [
        48,
        66,
        59,
        51,
        81,
        102,
        357,
        75,
        48,
        113
      ],
      [
        82,
        55,
        59,
        51,
        105,
        99,
        66,
        301,
        72,
        110
      ],
      [
        146,
        76,
        85,
        41,
        24,
        80,
        25,
        39,
        436,
        48
      ],
      [
        26,
        180,
        16,
        40,
        26,
        56,
        106,
        92,
        63,
        395
      ]
    ],
    "params": {
      "clf__C": 0.1,
      "clf__l1_ratio": 0.5
    },
    "accuracy": 0.3117,
    "cv_score": 0.30360001704322087
  }
}